tc420/__init__.py
tc420/__main__.py
tc420/tc420.py
tc420-0.2.1.dist-info/LICENSE
tc420-0.2.1.dist-info/METADATA
tc420-0.2.1.dist-info/WHEEL
tc420-0.2.1.dist-info/entry_points.txt
tc420-0.2.1.dist-info/top_level.txt
tc420-0.2.1.dist-info/RECORD
