Metadata-Version: 2.1
Name: tc420
Version: 0.2.1
Summary: TC420 LED Controller library and command line interface
Home-page: https://github.com/wallneradam/tc420
Author: Adam Wallner
Author-email: adam.wallner@gmail.com
License: GPLv3+
Platform: UNKNOWN
Classifier: Development Status :: 5 - Production/Stable
Classifier: License :: OSI Approved :: GNU General Public License v3 or later (GPLv3+)
Classifier: Operating System :: Microsoft :: Windows
Classifier: Operating System :: POSIX :: Linux
Classifier: Environment :: Console
Classifier: Programming Language :: Python :: 3
Classifier: Programming Language :: Python :: 3.5
Classifier: Topic :: Software Development :: Libraries :: Python Modules
Classifier: Topic :: System :: Hardware :: Hardware Drivers
Classifier: Topic :: Home Automation
Requires-Dist: pyusb
Requires-Dist: click
